pyobsidian/__init__.py
pyobsidian/adder.py
pyobsidian/adder_op.py
pyobsidian/filter.py
pyobsidian/formatter.py
pyobsidian/helpers.py
pyobsidian/markdown.py
pyobsidian/note.py
pyobsidian/searchby.py
pyobsidian/vault.py
pyobsidian-0.2.0.dist-info/LICENSE
pyobsidian-0.2.0.dist-info/METADATA
pyobsidian-0.2.0.dist-info/WHEEL
pyobsidian-0.2.0.dist-info/RECORD
