Metadata-Version: 2.1
Name: pyobsidian
Version: 0.2.0
Summary: Find and manipulate any note in your Obsidian vault
Home-page: https://github.com/matheussrod/pyobsidian
License: MIT
Author: Matheus S. Rodrigues
Author-email: matheus.srodr@gmail.com
Requires-Python: >=3.11,<4.0
Classifier: License :: OSI Approved :: MIT License
Classifier: Programming Language :: Python :: 3
Classifier: Programming Language :: Python :: 3.11
Classifier: Programming Language :: Python :: 3.12
Requires-Dist: pyyaml (>=6.0.1,<7.0.0)
Project-URL: Repository, https://github.com/matheussrod/pyobsidian
